fastss.cpython-38-i386-linux-gnu.so
jeta/__init__.py
jeta/archive/update.py
jeta/archive/units.py
jeta/archive/recovery.py
jeta/archive/cache.py
jeta/archive/utils.py
jeta/archive/operations.py
jeta/archive/status.py
jeta/archive/ingest.py
jeta/archive/file_defs.py
jeta/archive/pagination.py
jeta/archive/get_telem.py
jeta/archive/fetch.py
jeta/archive/__init__.py
jeta/archive/files.py
jeta/archive/plot.py
jeta/archive/derived/eps.py
jeta/archive/derived/thermal.py
jeta/archive/derived/base.py
jeta/archive/derived/orbit.py
jeta/archive/derived/test.py
jeta/archive/derived/acispow.py
jeta/archive/derived/pcad.py
jeta/archive/derived/__init__.py
jeta/archive/tests/test_orbit.py
jeta/archive/tests/test_archive_status_api.py
jeta/archive/tests/test_utils.py
jeta/archive/tests/test_fetch.py
jeta/archive/tests/__init__.py
jeta/config/properties.py
jeta/config/__init__.py
jeta/core/exceptions.py
jeta/core/__init__.py
jeta/staging/manage.py
jeta/staging/validation.py
jeta/staging/__init__.py
jeta-3.2.8.dist-info/top_level.txt
jeta-3.2.8.dist-info/WHEEL
jeta-3.2.8.dist-info/METADATA
jeta-3.2.8.dist-info/RECORD
jeta-3.2.8.dist-info/LICENSE.rst
jeta-3.2.8.data/scripts/create.archive.meta.sql
