Metadata-Version: 2.1
Name: jeta
Version: 3.2.8
Summary: Modules supporting JWST engineering telemetry archiving.
Home-page: https://github.com/spacetelescope/jeta
Author: David Kauffman
Author-email: dkauffman@stsci.edu
License: BSD 3-Clause
License-File: LICENSE.rst
Requires-Dist: Cython (==0.29.24)
Requires-Dist: numpy (==1.20.3)
Requires-Dist: pandas (==1.3.4)
Requires-Dist: astropy (==4.3.1)
Requires-Dist: torch (==1.10.0)
Requires-Dist: matplotlib (==3.4.3)
Requires-Dist: seaborn (==0.11.2)
Requires-Dist: plotly (==5.3.1)
Requires-Dist: numba (==0.54.1)
Requires-Dist: h5py (==3.5.0)
Requires-Dist: tables (==3.6.1)
Requires-Dist: pyyaks (==3.3.3)
